bayes_crypto_sdk/__init__.py
bayes_crypto_sdk/sentiment.py
bayes_crypto_sdk-0.1.1.dist-info/METADATA
bayes_crypto_sdk-0.1.1.dist-info/WHEEL
bayes_crypto_sdk-0.1.1.dist-info/top_level.txt
bayes_crypto_sdk-0.1.1.dist-info/RECORD
