Metadata-Version: 2.4
Name: bayes-crypto-sdk
Version: 0.1.1
Summary: SDK for MongoDB sentiment access
Home-page: https://pypi.org/project/bayes-crypto-sdk/
Author: afaan
Author-email: afaan@bayes.global
Classifier: Programming Language :: Python :: 3
Classifier: Operating System :: OS Independent
Requires-Python: >=3.7
Requires-Dist: pymongo>=3.12
Dynamic: author
Dynamic: author-email
Dynamic: classifier
Dynamic: description
Dynamic: description-content-type
Dynamic: home-page
Dynamic: requires-dist
Dynamic: requires-python
Dynamic: summary
